{"info":{"name":"Untitled","author":"Anonymous"},"switches":{"1,2":{"toggle":[{"pos":{"x":0,"y":0}}]},"2,1":{"toggle":[{"pos":{"x":0,"y":0}}]},"7,19":{"toggle":[{"pos":{"x":10,"y":19}},{"pos":{"x":10,"y":20}},{"pos":{"x":11,"y":18}},{"pos":{"x":11,"y":19}},{"pos":{"x":12,"y":17}},{"pos":{"x":12,"y":18}},{"pos":{"x":13,"y":17}}]},"9,21":{"toggle":[{"pos":{"x":10,"y":19}},{"pos":{"x":10,"y":20}},{"pos":{"x":11,"y":18}},{"pos":{"x":11,"y":19}},{"pos":{"x":12,"y":17}},{"pos":{"x":12,"y":18}},{"pos":{"x":13,"y":17}}]},"39,7":{"toggle":[{"pos":{"x":35,"y":11}},{"pos":{"x":36,"y":10}},{"pos":{"x":36,"y":11}},{"pos":{"x":37,"y":9}},{"pos":{"x":37,"y":10}},{"pos":{"x":38,"y":8}},{"pos":{"x":38,"y":9}}]},"41,9":{"toggle":[{"pos":{"x":38,"y":9}},{"pos":{"x":38,"y":8}},{"pos":{"x":37,"y":10}},{"pos":{"x":37,"y":9}},{"pos":{"x":36,"y":11}},{"pos":{"x":36,"y":10}},{"pos":{"x":35,"y":11}}]},"46,27":{"toggle":[{"pos":{"x":48,"y":28}}]},"47,26":{"toggle":[{"pos":{"x":48,"y":28}}]}},"fields":{"10,19":{"defaultState":"on"},"10,20":{"defaultState":"on"},"11,18":{"defaultState":"on"},"11,19":{"defaultState":"on"},"12,17":{"defaultState":"on"},"12,18":{"defaultState":"on"},"13,17":{"defaultState":"on"},"35,11":{"defaultState":"on"},"36,10":{"defaultState":"on"},"36,11":{"defaultState":"on"},"37,9":{"defaultState":"on"},"37,10":{"defaultState":"on"},"38,8":{"defaultState":"on"},"38,9":{"defaultState":"on"}},"portals":{}}