{"info":{"name":"Genesis","author":"Pizzarony"},"switches":{"5,13":{"toggle":[{"pos":{"x":1,"y":15}},{"pos":{"x":2,"y":15}},{"pos":{"x":3,"y":15}},{"pos":{"x":4,"y":15}}]},"5,31":{"toggle":[{"pos":{"x":1,"y":29}},{"pos":{"x":2,"y":29}},{"pos":{"x":3,"y":29}},{"pos":{"x":4,"y":29}}]},"7,20":{"toggle":[{"pos":{"x":1,"y":19}},{"pos":{"x":1,"y":20}},{"pos":{"x":1,"y":24}},{"pos":{"x":1,"y":25}},{"pos":{"x":2,"y":19}},{"pos":{"x":2,"y":20}},{"pos":{"x":2,"y":24}},{"pos":{"x":2,"y":25}},{"pos":{"x":3,"y":19}},{"pos":{"x":3,"y":20}},{"pos":{"x":3,"y":24}},{"pos":{"x":3,"y":25}},{"pos":{"x":4,"y":19}},{"pos":{"x":4,"y":20}},{"pos":{"x":4,"y":24}},{"pos":{"x":4,"y":25}}]},"7,24":{"toggle":[{"pos":{"x":1,"y":19}},{"pos":{"x":1,"y":20}},{"pos":{"x":1,"y":24}},{"pos":{"x":1,"y":25}},{"pos":{"x":2,"y":19}},{"pos":{"x":2,"y":20}},{"pos":{"x":2,"y":24}},{"pos":{"x":2,"y":25}},{"pos":{"x":3,"y":19}},{"pos":{"x":3,"y":20}},{"pos":{"x":3,"y":24}},{"pos":{"x":3,"y":25}},{"pos":{"x":4,"y":19}},{"pos":{"x":4,"y":20}},{"pos":{"x":4,"y":24}},{"pos":{"x":4,"y":25}}]},"19,9":{"toggle":[{"pos":{"x":22,"y":5}},{"pos":{"x":22,"y":6}},{"pos":{"x":22,"y":7}},{"pos":{"x":22,"y":8}}]},"19,10":{"toggle":[{"pos":{"x":22,"y":11}},{"pos":{"x":22,"y":12}},{"pos":{"x":22,"y":13}},{"pos":{"x":22,"y":14}}]},"19,20":{"toggle":[{"pos":{"x":22,"y":17}},{"pos":{"x":22,"y":18}},{"pos":{"x":22,"y":19}},{"pos":{"x":22,"y":20}}]},"19,24":{"toggle":[{"pos":{"x":22,"y":24}},{"pos":{"x":22,"y":25}},{"pos":{"x":22,"y":26}},{"pos":{"x":22,"y":27}}]},"19,34":{"toggle":[{"pos":{"x":22,"y":30}},{"pos":{"x":22,"y":31}},{"pos":{"x":22,"y":32}},{"pos":{"x":22,"y":33}}]},"19,35":{"toggle":[{"pos":{"x":22,"y":36}},{"pos":{"x":22,"y":37}},{"pos":{"x":22,"y":38}},{"pos":{"x":22,"y":39}}]}},"fields":{"1,15":{"defaultState":"off"},"1,19":{"defaultState":"on"},"1,20":{"defaultState":"on"},"1,24":{"defaultState":"on"},"1,25":{"defaultState":"on"},"1,29":{"defaultState":"off"},"2,15":{"defaultState":"off"},"2,19":{"defaultState":"on"},"2,20":{"defaultState":"on"},"2,24":{"defaultState":"on"},"2,25":{"defaultState":"on"},"2,29":{"defaultState":"off"},"3,15":{"defaultState":"off"},"3,19":{"defaultState":"on"},"3,20":{"defaultState":"on"},"3,24":{"defaultState":"on"},"3,25":{"defaultState":"on"},"3,29":{"defaultState":"off"},"4,15":{"defaultState":"off"},"4,19":{"defaultState":"on"},"4,20":{"defaultState":"on"},"4,24":{"defaultState":"on"},"4,25":{"defaultState":"on"},"4,29":{"defaultState":"off"},"22,5":{"defaultState":"off"},"22,6":{"defaultState":"off"},"22,7":{"defaultState":"off"},"22,8":{"defaultState":"off"},"22,11":{"defaultState":"off"},"22,12":{"defaultState":"off"},"22,13":{"defaultState":"off"},"22,14":{"defaultState":"off"},"22,17":{"defaultState":"off"},"22,18":{"defaultState":"off"},"22,19":{"defaultState":"off"},"22,20":{"defaultState":"off"},"22,24":{"defaultState":"off"},"22,25":{"defaultState":"off"},"22,26":{"defaultState":"off"},"22,27":{"defaultState":"off"},"22,30":{"defaultState":"off"},"22,31":{"defaultState":"off"},"22,32":{"defaultState":"off"},"22,33":{"defaultState":"off"},"22,36":{"defaultState":"off"},"22,37":{"defaultState":"off"},"22,38":{"defaultState":"off"},"22,39":{"defaultState":"off"}},"portals":{}}