{



    "info":
    {
	"name": "Cloudv2",
	"author": "Carp"
    },


    "switches": 
    {

       "17,16": 
       {
            "toggle": 
            [
                { "pos": { "x": 18, "y": 16 } },
                { "pos": { "x": 19, "y": 15 } },
                { "pos": { "x": 20, "y": 14 } },
		{ "pos": { "x": 18, "y": 17 } },
                { "pos": { "x": 19, "y": 16 } },
		{ "pos": { "x": 20, "y": 15 } },
                { "pos": { "x": 21, "y": 14 } }
            ]
       },
        
       "37,16": 
       {
            "toggle": 
            [
                { "pos": { "x": 34, "y": 14 } },
                { "pos": { "x": 35, "y": 15 } },
                { "pos": { "x": 36, "y": 16 } },
		{ "pos": { "x": 33, "y": 14 } },
                { "pos": { "x": 34, "y": 15 } },
                { "pos": { "x": 35, "y": 16 } },
		{ "pos": { "x": 36, "y": 17 } }
            ]
       }
    },

    "fields": 
    {
        "18,16" : { "defaultState": "off" },
        "19,17" : { "defaultState": "off" },
        "20,18" : { "defaultState": "off" },
        "34,18" : { "defaultState": "off" },
        "35,17" : { "defaultState": "off" },
        "36,16" : { "defaultState": "off" },
	"18,17" : { "defaultState": "off" },
        "19,16" : { "defaultState": "off" },
        "20,15" : { "defaultState": "off" },
        "21,14" : { "defaultState": "off" },
        "33,14" : { "defaultState": "off" },
        "34,15" : { "defaultState": "off" },
	"35,16" : { "defaultState": "off" },
        "36,17" : { "defaultState": "off" }
    }
}